{
  "products": [
    {
      "type": "electronics",
      "product_type_name": "Graphics Card",
      "product_name": "NVIDIA GeForce GTX 1660 Super",
      "manufacturer_name": "NVIDIA",
      "quantity": 1
    },
    {
      "type": "electronics",
      "product_type_name": "Earphones",
      "product_name": "Jaybird Vista 2",
      "manufacturer_name": "Jaybird",
      "quantity": 1
    },
    {
      "type": "electronics",
      "product_type_name": "Tablet",
      "product_name": "Google Pixel Slate",
      "manufacturer_name": "Google",
      "quantity": 1
    }
  ]
}